fibonacci/__init__.py
abhifibonacciseries-0.0.2.dist-info/LICENCE.txt
abhifibonacciseries-0.0.2.dist-info/METADATA
abhifibonacciseries-0.0.2.dist-info/WHEEL
abhifibonacciseries-0.0.2.dist-info/top_level.txt
abhifibonacciseries-0.0.2.dist-info/RECORD
